LICENSE.txt
MANIFEST.in
README.md
setup.py
prefpy_experiments/__init__.py
prefpy_experiments/gen_mixpl_datasets.py
prefpy_experiments/gmm_mixpl_nodata.py
prefpy_experiments/mixpl_defectiveparams.py
prefpy_experiments/mixpl_emm_exp.py
prefpy_experiments/mixpl_emm_exp1.py
prefpy_experiments/mixpl_emm_exp2.py
prefpy_experiments/mixpl_emm_exp3.py
prefpy_experiments/mixpl_experiments.py
prefpy_experiments/mixpl_experiments_matlab.py
prefpy_experiments/mixpl_experiments_mixingproportion.py
prefpy_experiments/mixpl_gmm_exp.py
prefpy_experiments/mixpl_gmm_exp1.py
prefpy_experiments/mm_gmm_experiments.py
prefpy_experiments/plot_mixpl.py
prefpy_experiments/plot_mixpl_emm.py
prefpy_experiments/plot_mixpl_emm1.py
prefpy_experiments/plot_mixpl_emm2.py
prefpy_experiments/plot_mixpl_emm3.py
prefpy_experiments/plot_mixpl_gmm.py
prefpy_experiments/plot_mixpl_gmm1.py
prefpy_experiments/plot_mixpl_matlab.py
prefpy_experiments/plot_mixpl_mixingproportion.py
prefpy_experiments/plot_mm_gmm.py
prefpy_experiments.egg-info/PKG-INFO
prefpy_experiments.egg-info/SOURCES.txt
prefpy_experiments.egg-info/dependency_links.txt
prefpy_experiments.egg-info/not-zip-safe
prefpy_experiments.egg-info/requires.txt
prefpy_experiments.egg-info/top_level.txt