Metadata-Version: 1.1
Name: prefpy-experiments
Version: 0.7.1
Summary: Rank aggregation algorithms
Home-page: https://github.com/pdpiech/prefpy_experiments
Author: Peter Piech
Author-email: UNKNOWN
License: GPL-3
Download-URL: https://github.com/pdpiech/prefpy_experiments/archive/v0.7.1.tar.gz
Platform: UNKNOWN
Classifier: Development Status :: 3 - Alpha
Classifier: License :: OSI Approved :: GNU General Public License v3 (GPLv3)
Classifier: Programming Language :: Python :: 3.4
Classifier: Programming Language :: Python :: 3.5
Classifier: Intended Audience :: Science/Research
Classifier: Topic :: Scientific/Engineering
